magen_logger/__init__.py
magen_logger/logger_config.py
magen_logger-1.0a1.dist-info/DESCRIPTION.rst
magen_logger-1.0a1.dist-info/METADATA
magen_logger-1.0a1.dist-info/RECORD
magen_logger-1.0a1.dist-info/WHEEL
magen_logger-1.0a1.dist-info/metadata.json
magen_logger-1.0a1.dist-info/top_level.txt
