Metadata-Version: 2.0
Name: magen-logger
Version: 1.0a1
Summary: Magen Logging Package
Home-page: http://www.cisco.com
Author: Alena Lifar
Author-email: alifar@cisco.com
License: Proprietary License
Platform: UNKNOWN
Classifier: Development Status :: 2 - Pre-Alpha
Classifier: Intended Audience :: Education
Classifier: Intended Audience :: Financial and Insurance Industry
Classifier: Intended Audience :: Healthcare Industry
Classifier: Intended Audience :: Legal Industry
Classifier: Topic :: Security
Classifier: License :: Other/Proprietary License
Classifier: Programming Language :: Python :: 3.5
Requires-Dist: Sphinx (>=1.6.3)
Requires-Dist: flake8 (>=3.3.0)
Requires-Dist: pytest (>=3.1.3)
Requires-Dist: wheel (>=0.30.0a0)
